[
  {
    "name": "Bank",
    "description": "An iconic encounter for LA SWAT forces, this map depicts an assault on a major bank. The focus is on providing a sense of progression for attackers as they make their way through progressively more fortified areas of the building.",
    "cover": {
      "src": "https://static.gametactic.eu/r6/maps/bank/cover.jpg",
      "width": 960,
      "height": 540,
      "format": "jpg"
    },
    "views": [
      {
        "id": "05d62c81-bd7c-4be7-99de-ba0f77119ca0",
        "name": "Basement",
        "image": {
          "src": "https://static.gametactic.eu/r6/maps/bank/basement.png",
          "width": 2560,
          "height": 1440,
          "format": "png"
        },
        "width": 2560,
        "height": 1440
      },
      {
        "id": "faa69a18-e82a-4244-8ff8-36c3193f097b",
        "name": "Ground",
        "image": {
          "src": "https://static.gametactic.eu/r6/maps/bank/ground.png",
          "width": 2560,
          "height": 1440,
          "format": "png"
        },
        "width": 2560,
        "height": 1440
      },
      {
        "id": "360684ad-6ebd-469c-b2f0-062cb5b30696",
        "name": "Floor 2",
        "image": {
          "src": "https://static.gametactic.eu/r6/maps/bank/floor2.png",
          "width": 2560,
          "height": 1440,
          "format": "png"
        },
        "width": 2560,
        "height": 1440
      },
      {
        "id": "723fe762-0ff7-4d21-a295-b81444bb955a",
        "name": "Roof",
        "image": {
          "src": "https://static.gametactic.eu/r6/maps/bank/roof.png",
          "width": 2560,
          "height": 1440,
          "format": "png"
        },
        "width": 2560,
        "height": 1440
      }
    ],
    "game": "r6",
    "teamConstructors": [
      {
        "name": "Attackers",
        "color": 12615425
      },
      {
        "name": "Defenders",
        "color": 955384
      }
    ]
  },
  {
    "name": "Yatch",
    "description": "In the Baffin Bay, a luxury yacht has crashed into an iceberg breaching the hull. Rainbow has been sent to secure the stranded vessel as an unidentified submarine has docked near the vessel.",
    "cover": {
      "src": "https://static.gametactic.eu/r6/maps/yatch/cover.jpg",
      "width": 600,
      "height": 337,
      "format": "jpg"
    },
    "views": [
      {
        "id": "d1e12e55-8d66-4b07-9e7d-a1426a607aad",
        "name": "Basement",
        "image": {
          "src": "https://static.gametactic.eu/r6/maps/yatch/basement.jpg",
          "width": 1600,
          "height": 900,
          "format": "jpg"
        },
        "width": 1600,
        "height": 900
      },
      {
        "id": "a870d662-7018-44d9-b378-bd90c0b81c48",
        "name": "Ground",
        "image": {
          "src": "https://static.gametactic.eu/r6/maps/yatch/ground.jpg",
          "width": 1600,
          "height": 900,
          "format": "jpg"
        },
        "width": 1600,
        "height": 900
      },
      {
        "id": "8d8998a5-2bcb-44e7-a88b-6692fcb0b16a",
        "name": "Floor 2",
        "image": {
          "src": "https://static.gametactic.eu/r6/maps/yatch/floor2.jpg",
          "width": 1600,
          "height": 900,
          "format": "jpg"
        },
        "width": 1600,
        "height": 900
      },
      {
        "id": "14a25564-4329-4c3a-a7ca-7a5a4c02c5c7",
        "name": "Floor 3",
        "image": {
          "src": "https://static.gametactic.eu/r6/maps/yatch/floor3.jpg",
          "width": 1600,
          "height": 900,
          "format": "jpg"
        },
        "width": 1600,
        "height": 900
      },
      {
        "id": "7784e7a4-d429-4981-979a-635fabd22103",
        "name": "Roof",
        "image": {
          "src": "https://static.gametactic.eu/r6/maps/yatch/roof.jpg",
          "width": 1600,
          "height": 900,
          "format": "jpg"
        },
        "width": 1600,
        "height": 900
      }
    ],
    "game": "r6",
    "teamConstructors": [
      {
        "name": "Attackers",
        "color": 12615425
      },
      {
        "name": "Defenders",
        "color": 955384
      }
    ]
  },
  {
    "name": "Border",
    "description": "Somewhere in Middle East, team Rainbow has been called in to assist local law enforcement regain control of the border. A mix of old and new construction and open air pathways, this is one of the most destructible and open maps in the game",
    "cover": {
      "src": "https://static.gametactic.eu/r6/maps/border/cover.jpg",
      "width": 600,
      "height": 337,
      "format": "jpg"
    },
    "views": [
      {
        "id": "829c7866-ce78-474b-a0e4-b3a243b3208d",
        "name": "Ground",
        "image": {
          "src": "https://static.gametactic.eu/r6/maps/border/ground.jpg",
          "width": 1600,
          "height": 900,
          "format": "jpg"
        },
        "width": 1600,
        "height": 900
      },
      {
        "id": "706681dc-3318-491f-bff7-fc08bed21817",
        "name": "Floor 2",
        "image": {
          "src": "https://static.gametactic.eu/r6/maps/border/floor2.jpg",
          "width": 1600,
          "height": 900,
          "format": "jpg"
        },
        "width": 1600,
        "height": 900
      },
      {
        "id": "e8db805d-8572-458e-8717-a2ec4d738044",
        "name": "Roof",
        "image": {
          "src": "https://static.gametactic.eu/r6/maps/border/roof.jpg",
          "width": 1600,
          "height": 900,
          "format": "jpg"
        },
        "width": 1600,
        "height": 900
      }
    ],
    "game": "r6",
    "teamConstructors": [
      {
        "name": "Attackers",
        "color": 12615425
      },
      {
        "name": "Defenders",
        "color": 955384
      }
    ]
  },
  {
    "name": "Chalet",
    "description": "A shootout in an “après-ski” chalet in the French alps, this area contrasts the warm, cozy mood of its interiors with the cold, constrained visibility of its exteriors.",
    "cover": {
      "src": "https://static.gametactic.eu/r6/maps/chalet/cover.jpg",
      "width": 480,
      "height": 270,
      "format": "jpg"
    },
    "views": [
      {
        "id": "4ff48af8-532a-416d-939f-9439da3497d8",
        "name": "Basement",
        "image": {
          "src": "https://static.gametactic.eu/r6/maps/chalet/basement.jpg",
          "width": 1600,
          "height": 900,
          "format": "jpg"
        },
        "width": 1600,
        "height": 900
      },
      {
        "id": "3568c70c-51f9-4595-9e90-b5a74878c9f8",
        "name": "Ground",
        "image": {
          "src": "https://static.gametactic.eu/r6/maps/chalet/ground.jpg",
          "width": 1600,
          "height": 900,
          "format": "jpg"
        },
        "width": 1600,
        "height": 900
      },
      {
        "id": "e1e3498c-e756-4296-8597-27187853a54f",
        "name": "Floor 2",
        "image": {
          "src": "https://static.gametactic.eu/r6/maps/chalet/floor2.jpg",
          "width": 1600,
          "height": 900,
          "format": "jpg"
        },
        "width": 1600,
        "height": 900
      },
      {
        "id": "b080930e-b433-4dc4-83ac-8cc9b8f84c73",
        "name": "Roof",
        "image": {
          "src": "https://static.gametactic.eu/r6/maps/chalet/roof.jpg",
          "width": 1600,
          "height": 900,
          "format": "jpg"
        },
        "width": 1600,
        "height": 900
      }
    ],
    "game": "r6",
    "teamConstructors": [
      {
        "name": "Attackers",
        "color": 12615425
      },
      {
        "name": "Defenders",
        "color": 955384
      }
    ]
  },
  {
    "name": "Clubhouse",
    "description": "This map depicts an assault on a biker gang clubhouse. Featuring a full bar, gaming tables and leather furniture, this mixed interior/exterior layout offers a host of interesting tactical possibilities for both attacker and defender.",
    "cover": {
      "src": "https://static.gametactic.eu/r6/maps/clubhouse/cover.jpg",
      "width": 480,
      "height": 270,
      "format": "jpg"
    },
    "views": [
      {
        "id": "da85f159-0cc4-4d73-8035-80b2278d9c62",
        "name": "Basement",
        "image": {
          "src": "https://static.gametactic.eu/r6/maps/clubhouse/basement.png",
          "width": 2560,
          "height": 1440,
          "format": "png"
        },
        "width": 2560,
        "height": 1440
      },
      {
        "id": "294f96bd-85b2-4c61-b977-79a83db69f95",
        "name": "Ground",
        "image": {
          "src": "https://static.gametactic.eu/r6/maps/clubhouse/ground.png",
          "width": 2560,
          "height": 1440,
          "format": "png"
        },
        "width": 2560,
        "height": 1440
      },
      {
        "id": "c4ab372b-990e-478c-9e0f-9d8d860fa442",
        "name": "Floor 2",
        "image": {
          "src": "https://static.gametactic.eu/r6/maps/clubhouse/floor2.png",
          "width": 2560,
          "height": 1440,
          "format": "png"
        },
        "width": 2560,
        "height": 1440
      },
      {
        "id": "9d33ee72-1b71-4e81-b52f-5a3173b8718d",
        "name": "Roof",
        "image": {
          "src": "https://static.gametactic.eu/r6/maps/clubhouse/roof.png",
          "width": 2560,
          "height": 1440,
          "format": "png"
        },
        "width": 2560,
        "height": 1440
      }
    ],
    "game": "r6",
    "teamConstructors": [
      {
        "name": "Attackers",
        "color": 12615425
      },
      {
        "name": "Defenders",
        "color": 955384
      }
    ]
  },
  {
    "name": "Coastline",
    "description": "Team Rainbow has been called to safeguard the seashore of Ibiza, Spain. Two of G.E.O.'s most resourceful Operators have been selected to provide their unique tactical expertise to the unit. Stationed on Ibiza’s rocky shore, course through Balearic ruins and navigate booming bars to neutralize the threat. Get ready for a surround flow of combat laced with chaotic rushes as you explore a paradise gone wrong",
    "cover": {
      "src": "https://static.gametactic.eu/r6/maps/coastline/cover.jpg",
      "width": 960,
      "height": 540,
      "format": "jpg"
    },
    "views": [
      {
        "id": "9f3dce4f-4cb6-4be9-a223-188178dee488",
        "name": "Floor 1",
        "image": {
          "src": "https://static.gametactic.eu/r6/maps/coastline/floor1.jpg",
          "width": 2560,
          "height": 1440,
          "format": "jpg"
        },
        "width": 2560,
        "height": 1440
      },
      {
        "id": "ea807f57-b2ac-494a-9afd-cc68e4f49f79",
        "name": "Floor 2",
        "image": {
          "src": "https://static.gametactic.eu/r6/maps/coastline/floor2.jpg",
          "width": 2560,
          "height": 1440,
          "format": "jpg"
        },
        "width": 2560,
        "height": 1440
      },
      {
        "id": "029d0bc1-469d-44ce-8479-018387935304",
        "name": "Roof",
        "image": {
          "src": "https://static.gametactic.eu/r6/maps/coastline/roof.jpg",
          "width": 2560,
          "height": 1440,
          "format": "jpg"
        },
        "width": 2560,
        "height": 1440
      }
    ],
    "game": "r6",
    "teamConstructors": [
      {
        "name": "Attackers",
        "color": 12615425
      },
      {
        "name": "Defenders",
        "color": 955384
      }
    ]
  },
  {
    "name": "Consulate",
    "description": "A high-risk, highly secured fortified location, this map depicts an assault on a French consulate in Ivory Coast.",
    "cover": {
      "src": "https://static.gametactic.eu/r6/maps/consulate/cover.jpg",
      "width": 480,
      "height": 270,
      "format": "jpg"
    },
    "views": [
      {
        "id": "26bed84b-88b3-4b12-aa3e-70262d7a1f37",
        "name": "Basement",
        "image": {
          "src": "https://static.gametactic.eu/r6/maps/consulate/basement.jpg",
          "width": 1600,
          "height": 900,
          "format": "jpg"
        },
        "width": 1600,
        "height": 900
      },
      {
        "id": "8f59852d-bfa9-4678-a793-22e2a3f9f25e",
        "name": "Ground",
        "image": {
          "src": "https://static.gametactic.eu/r6/maps/consulate/ground.jpg",
          "width": 1600,
          "height": 900,
          "format": "jpg"
        },
        "width": 1600,
        "height": 900
      },
      {
        "id": "258a95ac-d987-4126-bcbd-61b7845769ab",
        "name": "Floor 2",
        "image": {
          "src": "https://static.gametactic.eu/r6/maps/consulate/floor2.jpg",
          "width": 1600,
          "height": 900,
          "format": "jpg"
        },
        "width": 1600,
        "height": 900
      },
      {
        "id": "07f6d4b4-79ba-449a-8f63-cfe1068d111c",
        "name": "Roof",
        "image": {
          "src": "https://static.gametactic.eu/r6/maps/consulate/roof.jpg",
          "width": 1600,
          "height": 900,
          "format": "jpg"
        },
        "width": 1600,
        "height": 900
      }
    ],
    "game": "r6",
    "teamConstructors": [
      {
        "name": "Attackers",
        "color": 12615425
      },
      {
        "name": "Defenders",
        "color": 955384
      }
    ]
  },
  {
    "name": "Favela",
    "description": "Team Rainbow has been called to pacify and regain control of the Favela. Mixing colorful and narrow streets with high vantage points, this map supports exterior shell destruction which renders it as the most destructible to date.",
    "cover": {
      "src": "https://static.gametactic.eu/r6/maps/favela/cover.jpg",
      "width": 960,
      "height": 540,
      "format": "jpg"
    },
    "views": [
      {
        "id": "9445fa71-4be7-458f-94b8-6664beb1000c",
        "name": "Basement",
        "image": {
          "src": "https://static.gametactic.eu/r6/maps/favela/basement.jpg",
          "width": 1600,
          "height": 900,
          "format": "jpg"
        },
        "width": 1600,
        "height": 900
      },
      {
        "id": "48d99600-8fb2-48e3-b8c7-06045c823fc3",
        "name": "Ground",
        "image": {
          "src": "https://static.gametactic.eu/r6/maps/favela/ground.jpg",
          "width": 1600,
          "height": 900,
          "format": "jpg"
        },
        "width": 1600,
        "height": 900
      },
      {
        "id": "5d97a3ea-ed90-4026-b752-be83b0f75f8a",
        "name": "Floor 2",
        "image": {
          "src": "https://static.gametactic.eu/r6/maps/favela/floor2.jpg",
          "width": 1600,
          "height": 900,
          "format": "jpg"
        },
        "width": 1600,
        "height": 900
      },
      {
        "id": "a3ba91b9-f0f9-4c71-8154-24c480642b35",
        "name": "Floor 3",
        "image": {
          "src": "https://static.gametactic.eu/r6/maps/favela/floor3.jpg",
          "width": 1600,
          "height": 900,
          "format": "jpg"
        },
        "width": 1600,
        "height": 900
      },
      {
        "id": "ef1b253a-4078-4f33-8ba4-76d29ff09c37",
        "name": "Roof",
        "image": {
          "src": "https://static.gametactic.eu/r6/maps/favela/roof.jpg",
          "width": 1600,
          "height": 900,
          "format": "jpg"
        },
        "width": 1600,
        "height": 900
      }
    ],
    "game": "r6",
    "teamConstructors": [
      {
        "name": "Attackers",
        "color": 12615425
      },
      {
        "name": "Defenders",
        "color": 955384
      }
    ]
  },
  {
    "name": "Fortress",
    "description": "Appropriately called Fortress, the map is modeled after the distinct architecture of a Moroccan Kasbah, and is designed to offer Operators a variety of tactics.",
    "cover": {
      "src": "https://static.gametactic.eu/r6/maps/fortress/cover.jpg",
      "width": 480,
      "height": 270,
      "format": "jpg"
    },
    "views": [
      {
        "id": "71ddf2e1-9173-49cc-998b-d471fb60e26e",
        "name": "Floor 1",
        "image": {
          "src": "https://static.gametactic.eu/r6/maps/fortress/floor1.jpg",
          "width": 1600,
          "height": 900,
          "format": "jpg"
        },
        "width": 1600,
        "height": 900
      },
      {
        "id": "0f5ad996-0503-4159-9919-f27878fc4753",
        "name": "Floor 2",
        "image": {
          "src": "https://static.gametactic.eu/r6/maps/fortress/floor2.jpg",
          "width": 1600,
          "height": 900,
          "format": "jpg"
        },
        "width": 1600,
        "height": 900
      },
      {
        "id": "2d53589a-d1a6-40b9-b6ce-6a8598d4fe9e",
        "name": "Roof",
        "image": {
          "src": "https://static.gametactic.eu/r6/maps/fortress/roof.jpg",
          "width": 1600,
          "height": 900,
          "format": "jpg"
        },
        "width": 1600,
        "height": 900
      }
    ],
    "game": "r6",
    "teamConstructors": [
      {
        "name": "Attackers",
        "color": 12615425
      },
      {
        "name": "Defenders",
        "color": 955384
      }
    ]
  },
  {
    "name": "Hereford base",
    "description": "The CTU training grounds of the first and most iconic CTU. This is where SAS agents learn their craft and as such it a patchwork of plywood targets, sandbags, barbed wire and other obstacles. One of the most archetypal examples of siege gameplay.",
    "cover": {
      "src": "https://static.gametactic.eu/r6/maps/hereford_base/cover.jpg",
      "width": 480,
      "height": 270,
      "format": "jpg"
    },
    "views": [
      {
        "id": "cd879a96-d5ed-4481-9040-b732149ac4df",
        "name": "Basement",
        "image": {
          "src": "https://static.gametactic.eu/r6/maps/herefordbase/basement.jpg",
          "width": 1600,
          "height": 900,
          "format": "jpg"
        },
        "width": 1600,
        "height": 900
      },
      {
        "id": "784db7c5-198f-4bf3-b231-37ce3922b26f",
        "name": "Ground",
        "image": {
          "src": "https://static.gametactic.eu/r6/maps/herefordbase/ground.jpg",
          "width": 1600,
          "height": 900,
          "format": "jpg"
        },
        "width": 1600,
        "height": 900
      },
      {
        "id": "63a31d22-5365-4621-95eb-49181c62513a",
        "name": "Floor 2",
        "image": {
          "src": "https://static.gametactic.eu/r6/maps/herefordbase/floor2.jpg",
          "width": 1600,
          "height": 900,
          "format": "jpg"
        },
        "width": 1600,
        "height": 900
      },
      {
        "id": "5c048ef9-0b1b-44c4-a2b5-587dc465123e",
        "name": "Floor 3",
        "image": {
          "src": "https://static.gametactic.eu/r6/maps/herefordbase/floor3.jpg",
          "width": 1600,
          "height": 900,
          "format": "jpg"
        },
        "width": 1600,
        "height": 900
      },
      {
        "id": "0f327042-4bca-475c-9d27-9547c6dfec3a",
        "name": "Roof",
        "image": {
          "src": "https://static.gametactic.eu/r6/maps/herefordbase/roof.jpg",
          "width": 1600,
          "height": 900,
          "format": "jpg"
        },
        "width": 1600,
        "height": 900
      }
    ],
    "game": "r6",
    "teamConstructors": [
      {
        "name": "Attackers",
        "color": 12615425
      },
      {
        "name": "Defenders",
        "color": 955384
      }
    ]
  },
  {
    "name": "House",
    "description": "Playing on themes of familiarity and vulnerability, this encounter takes place in a typical suburban home. It’s a prime example of destructive depth and replayability, and is one of the showcases for classic siege gameplay.",
    "cover": {
      "src": "https://static.gametactic.eu/r6/maps/house/cover.jpg",
      "width": 300,
      "height": 168,
      "format": "jpg"
    },
    "views": [
      {
        "id": "9d4a9b31-5ccf-44c2-9fec-c0ba1c926ef8",
        "name": "Basement",
        "image": {
          "src": "https://static.gametactic.eu/r6/maps/house/basement.jpg",
          "width": 1600,
          "height": 900,
          "format": "jpg"
        },
        "width": 1600,
        "height": 900
      },
      {
        "id": "a3360465-d7fa-4dda-bdf3-10c6f49dc0e2",
        "name": "Ground",
        "image": {
          "src": "https://static.gametactic.eu/r6/maps/house/ground.jpg",
          "width": 1600,
          "height": 900,
          "format": "jpg"
        },
        "width": 1600,
        "height": 900
      },
      {
        "id": "217ba9da-531b-431e-aac3-48c4f9f133bd",
        "name": "Floor 2",
        "image": {
          "src": "https://static.gametactic.eu/r6/maps/house/floor2.jpg",
          "width": 1600,
          "height": 900,
          "format": "jpg"
        },
        "width": 1600,
        "height": 900
      },
      {
        "id": "dea45151-547a-4ad3-9d6b-f8340809f841",
        "name": "Roof",
        "image": {
          "src": "https://static.gametactic.eu/r6/maps/house/roof.jpg",
          "width": 1600,
          "height": 900,
          "format": "jpg"
        },
        "width": 1600,
        "height": 900
      }
    ],
    "game": "r6",
    "teamConstructors": [
      {
        "name": "Attackers",
        "color": 12615425
      },
      {
        "name": "Defenders",
        "color": 955384
      }
    ]
  },
  {
    "name": "Kafe Dostoyevsky",
    "description": "This high-class café in central Moscow is the pinnacle of glitz and glamour, and is a natural intervention ground for Spetsnaz forces. The grounds have been seized by terrorists at peak hours on Christmas Eve, and destruction of the rich, chic, classic decor will be a key element of this map.",
    "cover": {
      "src": "https://static.gametactic.eu/r6/maps/kafe_dostoyevsky/cover.jpg",
      "width": 480,
      "height": 270,
      "format": "jpg"
    },
    "views": [
      {
        "id": "b07b8630-99de-4056-a286-b4d4b9a3fe5c",
        "name": "Basement",
        "image": {
          "src": "https://static.gametactic.eu/r6/maps/kafedostoyevsky/basement.jpg",
          "width": 1600,
          "height": 900,
          "format": "jpg"
        },
        "width": 1600,
        "height": 900
      },
      {
        "id": "a1bbea56-f141-4876-b695-98a9b72094f9",
        "name": "Ground",
        "image": {
          "src": "https://static.gametactic.eu/r6/maps/kafedostoyevsky/ground.jpg",
          "width": 1600,
          "height": 900,
          "format": "jpg"
        },
        "width": 1600,
        "height": 900
      },
      {
        "id": "4a95baed-71d2-46ab-b37f-cc30a92f4789",
        "name": "Floor 2",
        "image": {
          "src": "https://static.gametactic.eu/r6/maps/kafedostoyevsky/floor2.jpg",
          "width": 1600,
          "height": 900,
          "format": "jpg"
        },
        "width": 1600,
        "height": 900
      },
      {
        "id": "dc48ecbf-21ca-4da8-ba9e-91d2a5768e00",
        "name": "Roof",
        "image": {
          "src": "https://static.gametactic.eu/r6/maps/kafedostoyevsky/roof.jpg",
          "width": 1600,
          "height": 900,
          "format": "jpg"
        },
        "width": 1600,
        "height": 900
      }
    ],
    "game": "r6",
    "teamConstructors": [
      {
        "name": "Attackers",
        "color": 12615425
      },
      {
        "name": "Defenders",
        "color": 955384
      }
    ]
  },
  {
    "name": "Kanal",
    "description": "Taking place in the industrial area of Hamburg, Germany, ‘Kanal’ involves multiple buildings with strategic connecting points over canals. It features many interesting strategic possibilities created by the many bridges, buildings and related vantage points of its terrain.",
    "cover": {
      "src": "https://static.gametactic.eu/r6/maps/kanal/cover.jpg",
      "width": 477,
      "height": 268,
      "format": "jpg"
    },
    "views": [
      {
        "id": "6d15a7f8-b410-4fe3-a385-649df73ceb29",
        "name": "Groundfloor",
        "image": {
          "src": "https://static.gametactic.eu/r6/maps/kanal/groundfloor.jpg",
          "width": 1600,
          "height": 900,
          "format": "jpg"
        },
        "width": 1600,
        "height": 900
      },
      {
        "id": "365562bb-b2c8-4140-ac0c-9c2c3b1e6722",
        "name": "Groundfloor 2",
        "image": {
          "src": "https://static.gametactic.eu/r6/maps/kanal/groundfloor2.jpg",
          "width": 1600,
          "height": 900,
          "format": "jpg"
        },
        "width": 1600,
        "height": 900
      },
      {
        "id": "2c81a6a1-a366-4dfc-a0a7-2cd0e33c2338",
        "name": "Floor 1",
        "image": {
          "src": "https://static.gametactic.eu/r6/maps/kanal/floor1.jpg",
          "width": 1600,
          "height": 900,
          "format": "jpg"
        },
        "width": 1600,
        "height": 900
      },
      {
        "id": "ed23610b-f2dc-4587-ab39-2601ab8d3151",
        "name": "Floor 2",
        "image": {
          "src": "https://static.gametactic.eu/r6/maps/kanal/floor2.jpg",
          "width": 1600,
          "height": 900,
          "format": "jpg"
        },
        "width": 1600,
        "height": 900
      },
      {
        "id": "95a3d255-502f-4a38-9d3a-dada6138a4b8",
        "name": "Roof",
        "image": {
          "src": "https://static.gametactic.eu/r6/maps/kanal/roof.jpg",
          "width": 1600,
          "height": 900,
          "format": "jpg"
        },
        "width": 1600,
        "height": 900
      }
    ],
    "game": "r6",
    "teamConstructors": [
      {
        "name": "Attackers",
        "color": 12615425
      },
      {
        "name": "Defenders",
        "color": 955384
      }
    ]
  },
  {
    "name": "Oregon",
    "description": "'Oregon' depicts an assault on a fortified survivalist compound. It feels rustic, eclectic and lived-in, and covers a vast, spread out layout requiring adapted tactics to sweep and hold effectively.",
    "cover": {
      "src": "https://static.gametactic.eu/r6/maps/oregon/cover.jpg",
      "width": 968,
      "height": 592,
      "format": "jpg"
    },
    "views": [
      {
        "id": "4e306bb4-b0f1-4305-a15f-eab4f8e224a6",
        "name": "Ground",
        "image": {
          "src": "https://static.gametactic.eu/r6/maps/oregon/ground.jpg",
          "width": 1600,
          "height": 900,
          "format": "jpg"
        },
        "width": 1600,
        "height": 900
      },
      {
        "id": "0803b938-59ef-47c4-99cd-5f3cfc87fd65",
        "name": "Floor 2",
        "image": {
          "src": "https://static.gametactic.eu/r6/maps/oregon/floor2.jpg",
          "width": 1600,
          "height": 900,
          "format": "jpg"
        },
        "width": 1600,
        "height": 900
      },
      {
        "id": "20d4777d-af17-42e2-9514-f9c156796f07",
        "name": "Floor 3",
        "image": {
          "src": "https://static.gametactic.eu/r6/maps/oregon/floor3.jpg",
          "width": 1600,
          "height": 900,
          "format": "jpg"
        },
        "width": 1600,
        "height": 900
      },
      {
        "id": "809d20a7-2dd4-4421-96ed-9bf138eabb22",
        "name": "Basement",
        "image": {
          "src": "https://static.gametactic.eu/r6/maps/oregon/basement.jpg",
          "width": 1600,
          "height": 900,
          "format": "jpg"
        },
        "width": 1600,
        "height": 900
      },
      {
        "id": "74f96c09-8d18-4a2c-93f2-f61392168084",
        "name": "Roof",
        "image": {
          "src": "https://static.gametactic.eu/r6/maps/oregon/roof.jpg",
          "width": 1600,
          "height": 900,
          "format": "jpg"
        },
        "width": 1600,
        "height": 900
      }
    ],
    "game": "r6",
    "teamConstructors": [
      {
        "name": "Attackers",
        "color": 12615425
      },
      {
        "name": "Defenders",
        "color": 955384
      }
    ]
  },
  {
    "name": "Outback",
    "description": "Set in Australia’s Red Heart, this map is an homage to all the dusty service stations and motels that populate the forgotten highways of the continent, places filled with hardworking locals and specialty menu items you’ll find nowhere else.",
    "cover": {
      "src": "https://static.gametactic.eu/r6/maps/outback/cover.jpg",
      "width": 480,
      "height": 270,
      "format": "jpg"
    },
    "views": [
      {
        "id": "c09f228f-34a2-43c6-b65d-1f81677d02b8",
        "name": "Floor 1",
        "image": {
          "src": "https://static.gametactic.eu/r6/maps/outback/floor1.jpg",
          "width": 1600,
          "height": 900,
          "format": "jpg"
        },
        "width": 1600,
        "height": 900
      },
      {
        "id": "b31a195a-fbf9-4763-b426-7f26891dc379",
        "name": "Floor 2",
        "image": {
          "src": "https://static.gametactic.eu/r6/maps/outback/floor2.jpg",
          "width": 1600,
          "height": 900,
          "format": "jpg"
        },
        "width": 1600,
        "height": 900
      },
      {
        "id": "1e1b181f-baa2-4b77-922b-337596dd87aa",
        "name": "Roof",
        "image": {
          "src": "https://static.gametactic.eu/r6/maps/outback/roof.jpg",
          "width": 1600,
          "height": 900,
          "format": "jpg"
        },
        "width": 1600,
        "height": 900
      }
    ],
    "game": "r6",
    "teamConstructors": [
      {
        "name": "Attackers",
        "color": 12615425
      },
      {
        "name": "Defenders",
        "color": 955384
      }
    ]
  },
  {
    "name": "Presidential Plane",
    "description": "One of the most iconic settings for a CTU operation, this presidential plane offers an exotic and unique siege experience. It is claustrophobic, tense and constrained, involving limited breaching opportunities and sight lines.",
    "cover": {
      "src": "https://static.gametactic.eu/r6/maps/presidential_plane/cover.jpg",
      "width": 478,
      "height": 265,
      "format": "jpg"
    },
    "views": [
      {
        "id": "ede1dd04-a2cc-4d68-ab39-5dd239d25092",
        "name": "Floor 1",
        "image": {
          "src": "https://static.gametactic.eu/r6/maps/presidentialplane/floor1.jpg",
          "width": 1600,
          "height": 900,
          "format": "jpg"
        },
        "width": 1600,
        "height": 900
      },
      {
        "id": "9ff5766b-4374-46db-97dc-5aef49e62d2c",
        "name": "Floor 2",
        "image": {
          "src": "https://static.gametactic.eu/r6/maps/presidentialplane/floor2.jpg",
          "width": 1600,
          "height": 900,
          "format": "jpg"
        },
        "width": 1600,
        "height": 900
      },
      {
        "id": "64e364df-9812-4c7a-ba89-43fb33d82151",
        "name": "Floor 3",
        "image": {
          "src": "https://static.gametactic.eu/r6/maps/presidentialplane/floor3.jpg",
          "width": 1600,
          "height": 900,
          "format": "jpg"
        },
        "width": 1600,
        "height": 900
      },
      {
        "id": "c0bc6fd9-ead7-476c-8ea3-b1b755a9ab00",
        "name": "Roof",
        "image": {
          "src": "https://static.gametactic.eu/r6/maps/presidentialplane/roof.jpg",
          "width": 1600,
          "height": 900,
          "format": "jpg"
        },
        "width": 1600,
        "height": 900
      }
    ],
    "game": "r6",
    "teamConstructors": [
      {
        "name": "Attackers",
        "color": 12615425
      },
      {
        "name": "Defenders",
        "color": 955384
      }
    ]
  },
  {
    "name": "Skyscraper",
    "description": "Perched on top of Skyscraper in Nagoya, Japan, you will explore refined works of Japanese architecture inside a dangerous mansion. Be prepared for vertiginous rappels in the haze of the morning sun, where modernity and tradition meet.",
    "cover": {
      "src": "https://static.gametactic.eu/r6/maps/skyscraper/cover.jpg",
      "width": 2640,
      "height": 1616,
      "format": "jpg"
    },
    "views": [
      {
        "id": "c65148c3-f3c5-48a2-ae09-a3429c2117ca",
        "name": "Floor 1",
        "image": {
          "src": "https://static.gametactic.eu/r6/maps/skyscraper/floor1.jpg",
          "width": 1600,
          "height": 900,
          "format": "jpg"
        },
        "width": 1600,
        "height": 900
      },
      {
        "id": "684066ce-3a03-4b58-9b2a-66d970274af2",
        "name": "Floor 2",
        "image": {
          "src": "https://static.gametactic.eu/r6/maps/skyscraper/floor2.jpg",
          "width": 1600,
          "height": 900,
          "format": "jpg"
        },
        "width": 1600,
        "height": 900
      },
      {
        "id": "b287d52d-c9a8-4a7d-b0dd-d9860418a8b0",
        "name": "Roof",
        "image": {
          "src": "https://static.gametactic.eu/r6/maps/skyscraper/roof.jpg",
          "width": 1600,
          "height": 900,
          "format": "jpg"
        },
        "width": 1600,
        "height": 900
      }
    ],
    "game": "r6",
    "teamConstructors": [
      {
        "name": "Attackers",
        "color": 12615425
      },
      {
        "name": "Defenders",
        "color": 955384
      }
    ]
  },
  {
    "name": "Theme Park",
    "description": "Team Rainbow has been called to raid an abandoned theme park on the shores of Hong Kong. Lead a lethal raid in this challenging perimeter. Get ready to discover a colorful and eclectic new map filled with dynamic and fast-paced face-offs.",
    "cover": {
      "src": "https://static.gametactic.eu/r6/maps/themepark/cover.jpg",
      "width": 600,
      "height": 337,
      "format": "jpg"
    },
    "views": [
      {
        "id": "7448fec5-bb71-4292-8b79-42ca099e9608",
        "name": "Floor 1",
        "image": {
          "src": "https://static.gametactic.eu/r6/maps/themepark/floor1.jpg",
          "width": 1600,
          "height": 900,
          "format": "jpg"
        },
        "width": 1600,
        "height": 900
      },
      {
        "id": "51a5c876-4c15-4e6d-adb6-c19d3ed3da77",
        "name": "Floor 2",
        "image": {
          "src": "https://static.gametactic.eu/r6/maps/themepark/floor2.jpg",
          "width": 1600,
          "height": 900,
          "format": "jpg"
        },
        "width": 1600,
        "height": 900
      },
      {
        "id": "9f7a0f09-da98-4fa8-9395-f20dba8d44ae",
        "name": "Roof",
        "image": {
          "src": "https://static.gametactic.eu/r6/maps/themepark/roof.jpg",
          "width": 1600,
          "height": 900,
          "format": "jpg"
        },
        "width": 1600,
        "height": 900
      }
    ],
    "game": "r6",
    "teamConstructors": [
      {
        "name": "Attackers",
        "color": 12615425
      },
      {
        "name": "Defenders",
        "color": 955384
      }
    ]
  },
  {
    "name": "Tower",
    "description": "Scale the snow-capped Mok Myeok Tower to lead a rescue mission in Seoul, South Korea. The modern communications and observation tower offers fresh vertical vantage points overlooking the entire cityscape, and sets the stage for diverse multilevel tactics.",
    "cover": {
      "src": "https://static.gametactic.eu/r6/maps/tower/cover.jpg",
      "width": 477,
      "height": 266,
      "format": "jpg"
    },
    "views": [
      {
        "id": "96c8e984-3e05-4d94-96c1-e51047cea16e",
        "name": "Floor 1",
        "image": {
          "src": "https://static.gametactic.eu/r6/maps/tower/floor1.jpg",
          "width": 1600,
          "height": 900,
          "format": "jpg"
        },
        "width": 1600,
        "height": 900
      },
      {
        "id": "9236ae20-639e-4c98-80ee-bebe925656d8",
        "name": "Floor 2",
        "image": {
          "src": "https://static.gametactic.eu/r6/maps/tower/floor2.jpg",
          "width": 1600,
          "height": 900,
          "format": "jpg"
        },
        "width": 1600,
        "height": 900
      },
      {
        "id": "6af4a234-2fe0-463b-b851-b89d2703a25a",
        "name": "Roof",
        "image": {
          "src": "https://static.gametactic.eu/r6/maps/tower/roof.jpg",
          "width": 1600,
          "height": 900,
          "format": "jpg"
        },
        "width": 1600,
        "height": 900
      }
    ],
    "game": "r6",
    "teamConstructors": [
      {
        "name": "Attackers",
        "color": 12615425
      },
      {
        "name": "Defenders",
        "color": 955384
      }
    ]
  },
  {
    "name": "Villa",
    "description": "The land belongs to the Vinciguerra, a dangerous crime family known for their smuggling activities. The house is their retreat, where they lead a lavish lifestyle and collect rare art pieces. Now we catch the villa in a snapshot of time: Vinciguerras are burning documents and transporting their holdings before the big raid. But they’ve got wind of Operation Para Bellum and fled, leaving everything in disarray with vital information ready for the taking.",
    "cover": {
      "src": "https://static.gametactic.eu/r6/maps/villa/cover.jpg",
      "width": 480,
      "height": 270,
      "format": "jpg"
    },
    "views": [
      {
        "id": "fd24fa5b-7275-47e1-a4a5-130cc5996d7d",
        "name": "Basement",
        "image": {
          "src": "https://static.gametactic.eu/r6/maps/villa/basement.jpg",
          "width": 1600,
          "height": 900,
          "format": "jpg"
        },
        "width": 1600,
        "height": 900
      },
      {
        "id": "5be732c6-6ee6-427b-947c-9551afa4ee3a",
        "name": "Floor 2",
        "image": {
          "src": "https://static.gametactic.eu/r6/maps/villa/floor2.jpg",
          "width": 1600,
          "height": 900,
          "format": "jpg"
        },
        "width": 1600,
        "height": 900
      },
      {
        "id": "c4170ce5-b88d-4fdb-ae84-f5b335b6bcd5",
        "name": "Floor 3",
        "image": {
          "src": "https://static.gametactic.eu/r6/maps/villa/floor3.jpg",
          "width": 1600,
          "height": 900,
          "format": "jpg"
        },
        "width": 1600,
        "height": 900
      },
      {
        "id": "81c296d9-03a6-4143-a293-f468d6458cbb",
        "name": "Roof",
        "image": {
          "src": "https://static.gametactic.eu/r6/maps/villa/roof.jpg",
          "width": 1600,
          "height": 900,
          "format": "jpg"
        },
        "width": 1600,
        "height": 900
      }
    ],
    "game": "r6",
    "teamConstructors": [
      {
        "name": "Attackers",
        "color": 12615425
      },
      {
        "name": "Defenders",
        "color": 955384
      }
    ]
  }
]
